tarpatch/__init__.py
tarpatch/__main__.py
tarpatch/cli.py
tarpatch-0.0.1.dist-info/LICENSE
tarpatch-0.0.1.dist-info/METADATA
tarpatch-0.0.1.dist-info/WHEEL
tarpatch-0.0.1.dist-info/entry_points.txt
tarpatch-0.0.1.dist-info/top_level.txt
tarpatch-0.0.1.dist-info/RECORD
