Metadata-Version: 2.1
Name: tarpatch
Version: 0.0.1
Summary: Binary patches for tarballs
Author-email: dennisvang <djvg@protonmail.com>
License: MIT License
Project-URL: source, https://github.com/dennisvang/tarpatch
Project-URL: documentation, https://github.com/dennisvang/tarpatch
Project-URL: issues, https://github.com/dennisvang/tarpatch/issues
Classifier: Programming Language :: Python :: 3
Classifier: License :: OSI Approved :: MIT License
Classifier: Operating System :: OS Independent
Requires-Python: >=3.9
License-File: LICENSE
Requires-Dist: bsdiff4 >=1.2.4
